SitanfuCs183cShandianshiKuozhangZhongwenBiji/README.md
SitanfuCs183cShandianshiKuozhangZhongwenBiji/__init__.py
SitanfuCs183cShandianshiKuozhangZhongwenBiji/__main__.py
SitanfuCs183cShandianshiKuozhangZhongwenBiji/file.epub
SitanfuCs183cShandianshiKuozhangZhongwenBiji/index.html
SitanfuCs183cShandianshiKuozhangZhongwenBiji/css/__init__.py
SitanfuCs183cShandianshiKuozhangZhongwenBiji/css/annotations.css
SitanfuCs183cShandianshiKuozhangZhongwenBiji/css/main.css
SitanfuCs183cShandianshiKuozhangZhongwenBiji/css/normalize.css
SitanfuCs183cShandianshiKuozhangZhongwenBiji/css/popup.css
SitanfuCs183cShandianshiKuozhangZhongwenBiji/font/__init__.py
SitanfuCs183cShandianshiKuozhangZhongwenBiji/font/fontello.eot
SitanfuCs183cShandianshiKuozhangZhongwenBiji/font/fontello.svg
SitanfuCs183cShandianshiKuozhangZhongwenBiji/font/fontello.ttf
SitanfuCs183cShandianshiKuozhangZhongwenBiji/font/fontello.woff
SitanfuCs183cShandianshiKuozhangZhongwenBiji/img/__init__.py
SitanfuCs183cShandianshiKuozhangZhongwenBiji/img/annotator-glyph-sprite.png
SitanfuCs183cShandianshiKuozhangZhongwenBiji/img/annotator-icon-sprite.png
SitanfuCs183cShandianshiKuozhangZhongwenBiji/img/apple-touch-icon.png
SitanfuCs183cShandianshiKuozhangZhongwenBiji/img/cancelfullscreen.png
SitanfuCs183cShandianshiKuozhangZhongwenBiji/img/close.png
SitanfuCs183cShandianshiKuozhangZhongwenBiji/img/fullscreen.png
SitanfuCs183cShandianshiKuozhangZhongwenBiji/img/loader.gif
SitanfuCs183cShandianshiKuozhangZhongwenBiji/img/menu-icon.png
SitanfuCs183cShandianshiKuozhangZhongwenBiji/img/save.png
SitanfuCs183cShandianshiKuozhangZhongwenBiji/img/saved.png
SitanfuCs183cShandianshiKuozhangZhongwenBiji/img/settings-s.png
SitanfuCs183cShandianshiKuozhangZhongwenBiji/img/settings.png
SitanfuCs183cShandianshiKuozhangZhongwenBiji/img/star.png
SitanfuCs183cShandianshiKuozhangZhongwenBiji/js/__init__.py
SitanfuCs183cShandianshiKuozhangZhongwenBiji/js/epub.js
SitanfuCs183cShandianshiKuozhangZhongwenBiji/js/epub.min.js
sitanfu_cs183c_shandianshi_kuozhang_zhongwen_biji-2024.3.3.0.dist-info/METADATA
sitanfu_cs183c_shandianshi_kuozhang_zhongwen_biji-2024.3.3.0.dist-info/WHEEL
sitanfu_cs183c_shandianshi_kuozhang_zhongwen_biji-2024.3.3.0.dist-info/entry_points.txt
sitanfu_cs183c_shandianshi_kuozhang_zhongwen_biji-2024.3.3.0.dist-info/top_level.txt
sitanfu_cs183c_shandianshi_kuozhang_zhongwen_biji-2024.3.3.0.dist-info/RECORD
